casrel_datautils_yyd/Base_Conf.py
casrel_datautils_yyd/__init__.py
casrel_datautils_yyd/data_loader.py
casrel_datautils_yyd/process.py
casrel_datautils_yyd-0.0.1.dist-info/licenses/License
casrel_datautils_yyd-0.0.1.dist-info/METADATA
casrel_datautils_yyd-0.0.1.dist-info/WHEEL
casrel_datautils_yyd-0.0.1.dist-info/top_level.txt
casrel_datautils_yyd-0.0.1.dist-info/RECORD
