Metadata-Version: 2.4
Name: casrel_datautils_yyd
Version: 0.0.1
Summary: A Chinese relation extraction data utility toolkit based on CasRel model
Home-page: https://github.com/yourusername/casrel_datautils
Author: YD.Y
Classifier: Programming Language :: Python :: 3
Classifier: License :: OSI Approved :: MIT License
Classifier: Operating System :: OS Independent
Requires-Python: >=3.7
License-File: License
Requires-Dist: torch
Requires-Dist: transformers>=4.0.0
Dynamic: author
Dynamic: classifier
Dynamic: description
Dynamic: description-content-type
Dynamic: home-page
Dynamic: license-file
Dynamic: requires-dist
Dynamic: requires-python
Dynamic: summary
